pybeamline/__init__.py
pybeamline/abstractevent.py
pybeamline/bevent.py
pybeamline/boevent.py
pybeamline/pybeamline.py
pybeamline/algorithms/__init__.py
pybeamline/algorithms/lambda_operator.py
pybeamline/algorithms/conformance/__init__.py
pybeamline/algorithms/conformance/behavioral/__init__.py
pybeamline/algorithms/conformance/behavioral/behavioral_conformance.py
pybeamline/algorithms/conformance/soft/__init__.py
pybeamline/algorithms/conformance/soft/pdfa_conformance.py
pybeamline/algorithms/conformance/soft/soft_conformance_report.py
pybeamline/algorithms/conformance/soft/soft_conformance_status.py
pybeamline/algorithms/conformance/soft/soft_conformance_tracker.py
pybeamline/algorithms/conformance/soft/weights_normalizer.py
pybeamline/algorithms/conformance/temporal_profile/__init__.py
pybeamline/algorithms/conformance/temporal_profile/temporal_profile_conformance.py
pybeamline/algorithms/discovery/__init__.py
pybeamline/algorithms/discovery/activity_entity_relation_miner_lossy_counting.py
pybeamline/algorithms/discovery/dfg_miner.py
pybeamline/algorithms/discovery/heuristics_miner_lossy_counting.py
pybeamline/algorithms/discovery/heuristics_miner_lossy_counting_budget.py
pybeamline/algorithms/discovery/temporal_profile.py
pybeamline/algorithms/oc/__init__.py
pybeamline/algorithms/oc/oc_merge_operator.py
pybeamline/algorithms/oc/oc_operator.py
pybeamline/algorithms/oc/strategies/__init__.py
pybeamline/algorithms/oc/strategies/base.py
pybeamline/filters/__init__.py
pybeamline/filters/filters.py
pybeamline/mappers/__init__.py
pybeamline/mappers/dfg_str_to_graphviz.py
pybeamline/mappers/infinite_size_directly_follows_mapper.py
pybeamline/mappers/print_operator.py
pybeamline/mappers/sliding_window_to_log.py
pybeamline/mappers/take_mapper.py
pybeamline/mappers/to_directly_follow_relations.py
pybeamline/mappers/windows.py
pybeamline/models/__init__.py
pybeamline/models/aer.py
pybeamline/models/incremental_mean.py
pybeamline/models/ocdfg.py
pybeamline-2.0.0.dist-info/licenses/LICENSE.txt
pybeamline-2.0.0.dist-info/METADATA
pybeamline-2.0.0.dist-info/WHEEL
pybeamline-2.0.0.dist-info/top_level.txt
pybeamline-2.0.0.dist-info/RECORD
