Metadata-Version: 2.4
Name: pybeamline
Version: 2.0.0
Summary: Streaming Process Mining
Author: Andrea Burattin
Project-URL: Homepage, https://beamline.cloud/
Project-URL: Issues, https://github.com/beamline/pybeamline/issues
Requires-Python: >=3.9
License-File: LICENSE.txt
Requires-Dist: graphviz<1.0,>=0.20
Requires-Dist: objsize~=0.7.0
Requires-Dist: paho-mqtt<3.0,>=2.1
Requires-Dist: pandas<3.0,>=2.2
Requires-Dist: pm4py>=2.7.19.3
Requires-Dist: pyais<3.0,>=2.8
Requires-Dist: reactivex==4.1.0
Requires-Dist: requests<3.0,>=2.31
Requires-Dist: river>=0.21.2
Requires-Dist: typing_extensions<5.0,>=4.0
Requires-Dist: numpy<3,>=1.26
Requires-Dist: matplotlib
Requires-Dist: imageio
Requires-Dist: pillow
Requires-Dist: ipython
Provides-Extra: dev
Requires-Dist: pytest; extra == "dev"
Requires-Dist: build; extra == "dev"
Requires-Dist: pip-tools; extra == "dev"
Requires-Dist: tox>=4.0; extra == "dev"
Provides-Extra: test
Requires-Dist: pytest; extra == "test"
Requires-Dist: coverage; extra == "test"
Dynamic: license-file
